{
    "source_path": "oot/",
    "source_md": "Observation of Thoughts.md",
    "output_md": "oot.mdx",
    "output_html": "oot.html",

    "BkImage": "oot.jpeg",

    "COPY_ENABLE": true,

    "ARW_DISPLAY": false,
    "ARW_HOVER_WIDTH": 6.7,
    "ARW_VISIBLE_WIDTH": 5,

    "SLDR_DISPLAY": true,

    "Page0_skip": false,
    
    "BkPage0_FontColor": "#89C2FF",
    "BkFontColor": "#abb8bb",
    "BkFontSize": "1em",   
    "BkPage0_Title": "Observation of Thoughts",
    "BkPage0_Description": "Sri Rao - Thoughts from reading, listening, walking and living in Chicago",
    "BkPage0_Tag": "Listen Read Walk and Live in Chicago",
    "BkPage0_Keywords": "Sri Rao - Thoughts, books, reading, Chicago",
    "BkPage0_head3": "~***~",
    "BkFontSizeMobile390": "0.9em",
    "BkListLink_show": true,
    "BkLinkURL": "https://sgrao001.github.io/MyBooks/AboutMe/AboutMe.html",

    "TitleFontClr": "#D4E6FF",
    "TitleFontSize": "0.8em",

    "Hide_page_number": false,

    "ImageWidthDesktop": "50%",
    "ImageWidthMobile": "95%",

    "TOC_TITLE": "Table of Contents",
    "TOC_POSITION": 0,
    "TOC_FontColor": "#4fc3f7",
    "TOC_ENABLE": true,
    "TOCasList": false
}